nonebot_plugin_grouptools/__init__.py
nonebot_plugin_grouptools/data.py
nonebot_plugin_grouptools/pb.py
nonebot_plugin_grouptools/player_status.py
nonebot_plugin_grouptools/utils.py
nonebot_plugin_bfvgrouptools-0.2.0.dist-info/METADATA
nonebot_plugin_bfvgrouptools-0.2.0.dist-info/WHEEL
nonebot_plugin_bfvgrouptools-0.2.0.dist-info/top_level.txt
nonebot_plugin_bfvgrouptools-0.2.0.dist-info/RECORD
