Metadata-Version: 2.4
Name: nonebot-plugin-bfvgrouptools
Version: 0.2.0
Summary: A Battlefield V group management plugin for NoneBot2
Author-email: llbuxudong <3513392931@qq.com>
License: MIT
Project-URL: Homepage, https://github.com/llbuxudong/nonebot-plugin-bfvgrouptools
Project-URL: Repository, https://github.com/llbuxudong/nonebot-plugin-bfvgrouptools
Project-URL: Documentation, https://github.com/llbuxudong/nonebot-plugin-bfvgrouptools#readme
Keywords: nonebot,nonebot2,battlefield,bfv,plugin
Classifier: Development Status :: 4 - Beta
Classifier: License :: OSI Approved :: MIT License
Classifier: Programming Language :: Python :: 3.10
Classifier: Programming Language :: Python :: 3.11
Requires-Python: >=3.10
Requires-Dist: nonebot2>=2.4.0
Requires-Dist: nonebot-adapter-onebot>=2.2.0
Requires-Dist: httpx>=0.23.0
Requires-Dist: aiocache>=0.11.1
Requires-Dist: pillow>=9.0.0
Requires-Dist: python-dotenv>=0.19.0
